stabilipy/__init__.py
stabilipy/dam.py
stabilipy/evaluation.py
stabilipy/export.py
stabilipy/load.py
stabilipy/pillar.py
stabilipy/report.py
stabilipy/segment.py
stabilipy/settings.py
stabilipy/stability.py
stabilipy-0.0.1.dist-info/LICENSE
stabilipy-0.0.1.dist-info/METADATA
stabilipy-0.0.1.dist-info/WHEEL
stabilipy-0.0.1.dist-info/top_level.txt
stabilipy-0.0.1.dist-info/RECORD
