Metadata-Version: 2.1
Name: stabilipy
Version: 0.0.1
Summary: Concrete-dam stability analyses
Home-page: https://github.com/timsta95/stabilipy
Author: timsta95
Author-email: stabilipy@gmail.com
License: UNKNOWN
Platform: UNKNOWN
Classifier: Programming Language :: Python :: 3
Classifier: License :: OSI Approved :: MIT License
Classifier: Operating System :: OS Independent
Requires-Python: >=3.7
License-File: LICENSE
